{
  "name": "LMDE Livreur",
  "short_name": "Livreur",
  "description": "Portail livreur — Le Monde de l'Esthétique",
  "start_url": "/livreur/login",
  "scope": "/livreur/",
  "display": "standalone",
  "background_color": "#fff7ed",
  "theme_color": "#f97316",
  "orientation": "portrait",
  "lang": "fr",
  "prefer_related_applications": false,
  "categories": ["business", "productivity"],
  "icons": [
    {
      "src": "/icons/icon-192.png",
      "sizes": "192x192",
      "type": "image/png",
      "purpose": "any"
    },
    {
      "src": "/icons/icon-192.png",
      "sizes": "192x192",
      "type": "image/png",
      "purpose": "maskable"
    },
    {
      "src": "/icons/icon-512.png",
      "sizes": "512x512",
      "type": "image/png",
      "purpose": "any"
    },
    {
      "src": "/icons/icon-512.png",
      "sizes": "512x512",
      "type": "image/png",
      "purpose": "maskable"
    }
  ]
}
